magnet_loss_iclr2016/__init__.py
magnet_loss_iclr2016/magnet_batcher.py
magnet_loss_iclr2016/magnet_loss.py
magnet_loss_iclr2016-0.0.4.dist-info/LICENSE
magnet_loss_iclr2016-0.0.4.dist-info/METADATA
magnet_loss_iclr2016-0.0.4.dist-info/WHEEL
magnet_loss_iclr2016-0.0.4.dist-info/top_level.txt
magnet_loss_iclr2016-0.0.4.dist-info/RECORD
