Metadata-Version: 2.1
Name: magnet-loss-iclr2016
Version: 0.0.4
Summary: Play a PIL Image list as a video
Home-page: https://github.com/heracleia/Magnet-Loss
Author: Kodur Krishna Chaitanya
Author-email: kodur.chaitanya@colorado.edu
License: UNKNOWN
Platform: UNKNOWN
Requires-Dist: faiss (>=1.7.0)
Requires-Dist: matplotlib (>=3.3.3)
Requires-Dist: numpy (>=1.19.2)
Requires-Dist: scikit-learn (>=0.23.2)
Requires-Dist: seaborn (>=0.11.1)
Requires-Dist: torch (>=1.7.1)
